alvin_test_package/__init__.py
alvin_test_package/number.py
alvin_test_package/version.py
alvin_test_package-0.0.1.dist-info/DESCRIPTION.rst
alvin_test_package-0.0.1.dist-info/METADATA
alvin_test_package-0.0.1.dist-info/RECORD
alvin_test_package-0.0.1.dist-info/WHEEL
alvin_test_package-0.0.1.dist-info/metadata.json
alvin_test_package-0.0.1.dist-info/top_level.txt
testNump/__init__.py
testNump/number.py
testNump/run.py
testNump/version.py
