Metadata-Version: 2.0
Name: alvin-test-package
Version: 0.0.1
Summary: A test project
Home-page: https://github.com/alvinhui/alvin_test_package
Author: Alvin Hui
Author-email: alvinxwt@gmail.com
License: MIT
Platform: UNKNOWN
Requires-Dist: numpy (>=1.13)
